[{"model": "admin.logentry", "pk": 1, "fields": {"action_time": "2023-07-15T05:52:36.373Z", "user": 1, "content_type": 7, "object_id": "1", "object_repr": "Mercedes A 180d", "action_flag": 1, "change_message": "[{\"added\": {}}, {\"added\": {\"name\": \"car image\", \"object\": \"Image: Mercedes\"}}, {\"added\": {\"name\": \"car image\", \"object\": \"Image: Mercedes\"}}, {\"added\": {\"name\": \"car image\", \"object\": \"Image: Mercedes\"}}, {\"added\": {\"name\": \"car image\", \"object\": \"Image: Mercedes\"}}]"}}, {"model": "admin.logentry", "pk": 2, "fields": {"action_time": "2023-07-15T05:57:18.338Z", "user": 1, "content_type": 7, "object_id": "2", "object_repr": "Audi A1", "action_flag": 1, "change_message": "[{\"added\": {}}, {\"added\": {\"name\": \"car image\", \"object\": \"Image: Audi\"}}, {\"added\": {\"name\": \"car image\", \"object\": \"Image: Audi\"}}, {\"added\": {\"name\": \"car image\", \"object\": \"Image: Audi\"}}]"}}, {"model": "admin.logentry", "pk": 3, "fields": {"action_time": "2023-07-15T06:01:01.824Z", "user": 1, "content_type": 7, "object_id": "3", "object_repr": "Fiat 500C", "action_flag": 1, "change_message": "[{\"added\": {}}, {\"added\": {\"name\": \"car image\", \"object\": \"Image: Fiat\"}}, {\"added\": {\"name\": \"car image\", \"object\": \"Image: Fiat\"}}, {\"added\": {\"name\": \"car image\", \"object\": \"Image: Fiat\"}}]"}}, {"model": "admin.logentry", "pk": 4, "fields": {"action_time": "2023-07-15T06:01:24.011Z", "user": 1, "content_type": 7, "object_id": "2", "object_repr": "Audi A1", "action_flag": 2, "change_message": "[{\"changed\": {\"fields\": [\"Details\"]}}]"}}, {"model": "admin.logentry", "pk": 5, "fields": {"action_time": "2023-07-15T06:01:42.552Z", "user": 1, "content_type": 7, "object_id": "1", "object_repr": "Mercedes A 180d", "action_flag": 2, "change_message": "[{\"changed\": {\"fields\": [\"Details\"]}}]"}}, {"model": "admin.logentry", "pk": 6, "fields": {"action_time": "2023-07-15T06:04:53.229Z", "user": 1, "content_type": 7, "object_id": "4", "object_repr": "Porsche Cayenne", "action_flag": 1, "change_message": "[{\"added\": {}}, {\"added\": {\"name\": \"car image\", \"object\": \"Image: Porsche\"}}, {\"added\": {\"name\": \"car image\", \"object\": \"Image: Porsche\"}}, {\"added\": {\"name\": \"car image\", \"object\": \"Image: Porsche\"}}]"}}, {"model": "admin.logentry", "pk": 7, "fields": {"action_time": "2023-07-15T06:07:56.480Z", "user": 1, "content_type": 7, "object_id": "5", "object_repr": "MINI Cooper D Countryman", "action_flag": 1, "change_message": "[{\"added\": {}}, {\"added\": {\"name\": \"car image\", \"object\": \"Image: MINI\"}}, {\"added\": {\"name\": \"car image\", \"object\": \"Image: MINI\"}}, {\"added\": {\"name\": \"car image\", \"object\": \"Image: MINI\"}}]"}}, {"model": "admin.logentry", "pk": 8, "fields": {"action_time": "2023-07-15T06:11:33.703Z", "user": 1, "content_type": 7, "object_id": "6", "object_repr": "Ferrari GTC4 Lusso", "action_flag": 1, "change_message": "[{\"added\": {}}, {\"added\": {\"name\": \"car image\", \"object\": \"Image: Ferrari\"}}, {\"added\": {\"name\": \"car image\", \"object\": \"Image: Ferrari\"}}, {\"added\": {\"name\": \"car image\", \"object\": \"Image: Ferrari\"}}]"}}, {"model": "admin.logentry", "pk": 9, "fields": {"action_time": "2023-07-15T09:08:31.957Z", "user": 1, "content_type": 7, "object_id": "7", "object_repr": "Fiat 500", "action_flag": 1, "change_message": "[{\"added\": {}}, {\"added\": {\"name\": \"car image\", \"object\": \"Image: Fiat\"}}, {\"added\": {\"name\": \"car image\", \"object\": \"Image: Fiat\"}}, {\"added\": {\"name\": \"car image\", \"object\": \"Image: Fiat\"}}]"}}, {"model": "admin.logentry", "pk": 10, "fields": {"action_time": "2023-07-15T09:16:24.828Z", "user": 1, "content_type": 7, "object_id": "8", "object_repr": "Audi Q3", "action_flag": 1, "change_message": "[{\"added\": {}}, {\"added\": {\"name\": \"car image\", \"object\": \"Image: Audi\"}}, {\"added\": {\"name\": \"car image\", \"object\": \"Image: Audi\"}}, {\"added\": {\"name\": \"car image\", \"object\": \"Image: Audi\"}}]"}}, {"model": "admin.logentry", "pk": 11, "fields": {"action_time": "2023-07-17T15:33:20.549Z", "user": 1, "content_type": 4, "object_id": "2", "object_repr": "alessiomirra", "action_flag": 1, "change_message": "[{\"added\": {}}]"}}, {"model": "admin.logentry", "pk": 12, "fields": {"action_time": "2023-07-17T15:33:54.652Z", "user": 1, "content_type": 4, "object_id": "2", "object_repr": "alessiomirra", "action_flag": 2, "change_message": "[{\"changed\": {\"fields\": [\"First name\", \"Last name\", \"Email address\", \"Staff status\"]}}]"}}, {"model": "admin.logentry", "pk": 13, "fields": {"action_time": "2023-07-17T15:34:50.257Z", "user": 1, "content_type": 4, "object_id": "2", "object_repr": "alessiomirra", "action_flag": 2, "change_message": "[{\"changed\": {\"fields\": [\"User permissions\"]}}]"}}, {"model": "admin.logentry", "pk": 14, "fields": {"action_time": "2023-07-18T16:37:00.538Z", "user": 1, "content_type": 7, "object_id": "9", "object_repr": "òd wdwd", "action_flag": 3, "change_message": ""}}, {"model": "admin.logentry", "pk": 15, "fields": {"action_time": "2023-07-20T06:17:30.152Z", "user": 1, "content_type": 7, "object_id": "7", "object_repr": "Fiat 500", "action_flag": 3, "change_message": ""}}, {"model": "admin.logentry", "pk": 16, "fields": {"action_time": "2023-07-20T06:17:30.155Z", "user": 1, "content_type": 7, "object_id": "6", "object_repr": "Ferrari GTC4 Lusso", "action_flag": 3, "change_message": ""}}, {"model": "admin.logentry", "pk": 17, "fields": {"action_time": "2023-07-20T06:17:30.156Z", "user": 1, "content_type": 7, "object_id": "5", "object_repr": "MINI Cooper D Countryman", "action_flag": 3, "change_message": ""}}, {"model": "admin.logentry", "pk": 18, "fields": {"action_time": "2023-07-20T06:17:30.157Z", "user": 1, "content_type": 7, "object_id": "4", "object_repr": "Porsche Cayenne", "action_flag": 3, "change_message": ""}}, {"model": "admin.logentry", "pk": 19, "fields": {"action_time": "2023-07-20T06:17:30.159Z", "user": 1, "content_type": 7, "object_id": "3", "object_repr": "Fiat 500C", "action_flag": 3, "change_message": ""}}, {"model": "admin.logentry", "pk": 20, "fields": {"action_time": "2023-07-20T06:17:30.160Z", "user": 1, "content_type": 7, "object_id": "2", "object_repr": "Audi A1", "action_flag": 3, "change_message": ""}}, {"model": "admin.logentry", "pk": 21, "fields": {"action_time": "2023-07-20T06:17:30.160Z", "user": 1, "content_type": 7, "object_id": "1", "object_repr": "Mercedes A 180d", "action_flag": 3, "change_message": ""}}, {"model": "admin.logentry", "pk": 22, "fields": {"action_time": "2023-07-22T16:16:25.747Z", "user": 1, "content_type": 7, "object_id": "8", "object_repr": "Mercedes B 180", "action_flag": 1, "change_message": "[{\"added\": {}}]"}}, {"model": "admin.logentry", "pk": 23, "fields": {"action_time": "2023-07-24T07:04:25.081Z", "user": 1, "content_type": 7, "object_id": "1", "object_repr": "Fiat 500", "action_flag": 2, "change_message": "[{\"changed\": {\"fields\": [\"Miniature\"]}}]"}}, {"model": "admin.logentry", "pk": 24, "fields": {"action_time": "2023-07-24T07:05:22.471Z", "user": 1, "content_type": 4, "object_id": "2", "object_repr": "alessiomirra", "action_flag": 2, "change_message": "[{\"changed\": {\"fields\": [\"User permissions\"]}}]"}}, {"model": "admin.logentry", "pk": 25, "fields": {"action_time": "2023-07-24T07:15:14.167Z", "user": 1, "content_type": 12, "object_id": "1", "object_repr": "company-informations", "action_flag": 1, "change_message": "[{\"added\": {}}]"}}, {"model": "admin.logentry", "pk": 26, "fields": {"action_time": "2023-07-24T07:15:19.225Z", "user": 1, "content_type": 12, "object_id": "1", "object_repr": "company-informations", "action_flag": 2, "change_message": "[]"}}, {"model": "admin.logentry", "pk": 27, "fields": {"action_time": "2023-07-24T07:16:21.397Z", "user": 1, "content_type": 4, "object_id": "2", "object_repr": "alessiomirra", "action_flag": 2, "change_message": "[{\"changed\": {\"fields\": [\"User permissions\"]}}]"}}, {"model": "admin.logentry", "pk": 28, "fields": {"action_time": "2023-07-24T10:22:12.790Z", "user": 2, "content_type": 12, "object_id": "1", "object_repr": "company-informations", "action_flag": 2, "change_message": "[{\"changed\": {\"fields\": [\"Email\"]}}]"}}, {"model": "auth.permission", "pk": 1, "fields": {"name": "Can add log entry", "content_type": 1, "codename": "add_logentry"}}, {"model": "auth.permission", "pk": 2, "fields": {"name": "Can change log entry", "content_type": 1, "codename": "change_logentry"}}, {"model": "auth.permission", "pk": 3, "fields": {"name": "Can delete log entry", "content_type": 1, "codename": "delete_logentry"}}, {"model": "auth.permission", "pk": 4, "fields": {"name": "Can view log entry", "content_type": 1, "codename": "view_logentry"}}, {"model": "auth.permission", "pk": 5, "fields": {"name": "Can add permission", "content_type": 2, "codename": "add_permission"}}, {"model": "auth.permission", "pk": 6, "fields": {"name": "Can change permission", "content_type": 2, "codename": "change_permission"}}, {"model": "auth.permission", "pk": 7, "fields": {"name": "Can delete permission", "content_type": 2, "codename": "delete_permission"}}, {"model": "auth.permission", "pk": 8, "fields": {"name": "Can view permission", "content_type": 2, "codename": "view_permission"}}, {"model": "auth.permission", "pk": 9, "fields": {"name": "Can add group", "content_type": 3, "codename": "add_group"}}, {"model": "auth.permission", "pk": 10, "fields": {"name": "Can change group", "content_type": 3, "codename": "change_group"}}, {"model": "auth.permission", "pk": 11, "fields": {"name": "Can delete group", "content_type": 3, "codename": "delete_group"}}, {"model": "auth.permission", "pk": 12, "fields": {"name": "Can view group", "content_type": 3, "codename": "view_group"}}, {"model": "auth.permission", "pk": 13, "fields": {"name": "Can add user", "content_type": 4, "codename": "add_user"}}, {"model": "auth.permission", "pk": 14, "fields": {"name": "Can change user", "content_type": 4, "codename": "change_user"}}, {"model": "auth.permission", "pk": 15, "fields": {"name": "Can delete user", "content_type": 4, "codename": "delete_user"}}, {"model": "auth.permission", "pk": 16, "fields": {"name": "Can view user", "content_type": 4, "codename": "view_user"}}, {"model": "auth.permission", "pk": 17, "fields": {"name": "Can add content type", "content_type": 5, "codename": "add_contenttype"}}, {"model": "auth.permission", "pk": 18, "fields": {"name": "Can change content type", "content_type": 5, "codename": "change_contenttype"}}, {"model": "auth.permission", "pk": 19, "fields": {"name": "Can delete content type", "content_type": 5, "codename": "delete_contenttype"}}, {"model": "auth.permission", "pk": 20, "fields": {"name": "Can view content type", "content_type": 5, "codename": "view_contenttype"}}, {"model": "auth.permission", "pk": 21, "fields": {"name": "Can add session", "content_type": 6, "codename": "add_session"}}, {"model": "auth.permission", "pk": 22, "fields": {"name": "Can change session", "content_type": 6, "codename": "change_session"}}, {"model": "auth.permission", "pk": 23, "fields": {"name": "Can delete session", "content_type": 6, "codename": "delete_session"}}, {"model": "auth.permission", "pk": 24, "fields": {"name": "Can view session", "content_type": 6, "codename": "view_session"}}, {"model": "auth.permission", "pk": 25, "fields": {"name": "Can add car", "content_type": 7, "codename": "add_car"}}, {"model": "auth.permission", "pk": 26, "fields": {"name": "Can change car", "content_type": 7, "codename": "change_car"}}, {"model": "auth.permission", "pk": 27, "fields": {"name": "Can delete car", "content_type": 7, "codename": "delete_car"}}, {"model": "auth.permission", "pk": 28, "fields": {"name": "Can view car", "content_type": 7, "codename": "view_car"}}, {"model": "auth.permission", "pk": 29, "fields": {"name": "Can add car image", "content_type": 8, "codename": "add_carimage"}}, {"model": "auth.permission", "pk": 30, "fields": {"name": "Can change car image", "content_type": 8, "codename": "change_carimage"}}, {"model": "auth.permission", "pk": 31, "fields": {"name": "Can delete car image", "content_type": 8, "codename": "delete_carimage"}}, {"model": "auth.permission", "pk": 32, "fields": {"name": "Can view car image", "content_type": 8, "codename": "view_carimage"}}, {"model": "auth.permission", "pk": 33, "fields": {"name": "Can add Token", "content_type": 9, "codename": "add_token"}}, {"model": "auth.permission", "pk": 34, "fields": {"name": "Can change Token", "content_type": 9, "codename": "change_token"}}, {"model": "auth.permission", "pk": 35, "fields": {"name": "Can delete Token", "content_type": 9, "codename": "delete_token"}}, {"model": "auth.permission", "pk": 36, "fields": {"name": "Can view Token", "content_type": 9, "codename": "view_token"}}, {"model": "auth.permission", "pk": 37, "fields": {"name": "Can add token", "content_type": 10, "codename": "add_tokenproxy"}}, {"model": "auth.permission", "pk": 38, "fields": {"name": "Can change token", "content_type": 10, "codename": "change_tokenproxy"}}, {"model": "auth.permission", "pk": 39, "fields": {"name": "Can delete token", "content_type": 10, "codename": "delete_tokenproxy"}}, {"model": "auth.permission", "pk": 40, "fields": {"name": "Can view token", "content_type": 10, "codename": "view_tokenproxy"}}, {"model": "auth.permission", "pk": 41, "fields": {"name": "Can add subscriber", "content_type": 11, "codename": "add_subscriber"}}, {"model": "auth.permission", "pk": 42, "fields": {"name": "Can change subscriber", "content_type": 11, "codename": "change_subscriber"}}, {"model": "auth.permission", "pk": 43, "fields": {"name": "Can delete subscriber", "content_type": 11, "codename": "delete_subscriber"}}, {"model": "auth.permission", "pk": 44, "fields": {"name": "Can view subscriber", "content_type": 11, "codename": "view_subscriber"}}, {"model": "auth.permission", "pk": 45, "fields": {"name": "Can add company info", "content_type": 12, "codename": "add_companyinfo"}}, {"model": "auth.permission", "pk": 46, "fields": {"name": "Can change company info", "content_type": 12, "codename": "change_companyinfo"}}, {"model": "auth.permission", "pk": 47, "fields": {"name": "Can delete company info", "content_type": 12, "codename": "delete_companyinfo"}}, {"model": "auth.permission", "pk": 48, "fields": {"name": "Can view company info", "content_type": 12, "codename": "view_companyinfo"}}, {"model": "auth.user", "pk": 1, "fields": {"password": "pbkdf2_sha256$600000$p1SpGjpvhLvQMAj6TLntXq$HiDoOSSDECMxolOVhjpFt42AlIHVRRn4/bde4oSRvCI=", "last_login": "2023-07-24T07:14:17.802Z", "is_superuser": true, "username": "admin", "first_name": "", "last_name": "", "email": "alessiomirra97@gmail.com", "is_staff": true, "is_active": true, "date_joined": "2023-07-09T06:48:03.418Z", "groups": [], "user_permissions": []}}, {"model": "auth.user", "pk": 2, "fields": {"password": "pbkdf2_sha256$600000$IeK4qIyORyIsmJfdMfMqVI$okj/XXgUNCD1j4t/1LqC3y6sGPS1ZkVuhBMcyVLe788=", "last_login": "2023-07-24T10:22:02.125Z", "is_superuser": false, "username": "alessiomirra", "first_name": "Alessio", "last_name": "Mirra", "email": "alessiomirra97@gmail.com", "is_staff": true, "is_active": true, "date_joined": "2023-07-17T15:33:20Z", "groups": [], "user_permissions": [25, 26, 27, 28, 46]}}, {"model": "contenttypes.contenttype", "pk": 1, "fields": {"app_label": "admin", "model": "logentry"}}, {"model": "contenttypes.contenttype", "pk": 2, "fields": {"app_label": "auth", "model": "permission"}}, {"model": "contenttypes.contenttype", "pk": 3, "fields": {"app_label": "auth", "model": "group"}}, {"model": "contenttypes.contenttype", "pk": 4, "fields": {"app_label": "auth", "model": "user"}}, {"model": "contenttypes.contenttype", "pk": 5, "fields": {"app_label": "contenttypes", "model": "contenttype"}}, {"model": "contenttypes.contenttype", "pk": 6, "fields": {"app_label": "sessions", "model": "session"}}, {"model": "contenttypes.contenttype", "pk": 7, "fields": {"app_label": "cars", "model": "car"}}, {"model": "contenttypes.contenttype", "pk": 8, "fields": {"app_label": "cars", "model": "carimage"}}, {"model": "contenttypes.contenttype", "pk": 9, "fields": {"app_label": "authtoken", "model": "token"}}, {"model": "contenttypes.contenttype", "pk": 10, "fields": {"app_label": "authtoken", "model": "tokenproxy"}}, {"model": "contenttypes.contenttype", "pk": 11, "fields": {"app_label": "newsletter", "model": "subscriber"}}, {"model": "contenttypes.contenttype", "pk": 12, "fields": {"app_label": "cars", "model": "companyinfo"}}, {"model": "sessions.session", "pk": "0fyxh99qf57ixpces8v15c176eosmsdp", "fields": {"session_data": ".eJxVjEEOwiAQRe_C2hCgTKEu3XsGMgODVA0kpV0Z765NutDtf-_9lwi4rSVsnZcwJ3EWWpx-N8L44LqDdMd6azK2ui4zyV2RB-3y2hI_L4f7d1Cwl2-tImlEl_PklcoenNUjO5VHAJ5MTOyBIkfWxlg7aM1kfAJQwIbS4K14fwDpQzfN:1qNFFy:0cGYerwfMdp8fZIqdpTrgSvD-76b9jshlvhA0QL2F5I", "expire_date": "2023-08-05T16:14:58.031Z"}}, {"model": "sessions.session", "pk": "1bkctzwwkq6ip50ktj8aurjtmaa080az", "fields": {"session_data": ".eJxVjEEOwiAQRe_C2hCgTKEu3XsGMgODVA0kpV0Z765NutDtf-_9lwi4rSVsnZcwJ3EWWpx-N8L44LqDdMd6azK2ui4zyV2RB-3y2hI_L4f7d1Cwl2-tImlEl_PklcoenNUjO5VHAJ5MTOyBIkfWxlg7aM1kfAJQwIbS4K14fwDpQzfN:1qN7LE:-eC7IO5TDr0RConCRKC6x1stpRfS8Yv4APIt4KyGAMI", "expire_date": "2023-08-05T07:47:52.631Z"}}, {"model": "sessions.session", "pk": "1gemvtfqron5agmprbtc7y52hcfr68qy", "fields": {"session_data": ".eJxVjMsOwiAQRf-FtSE4yMul-34DgZlBqoYmpV0Z_92QdKHbe865bxHTvtW4d17jTOIqQJx-t5zwyW0AeqR2XyQubVvnLIciD9rltBC_bof7d1BTr6MmT6C1QQWqEHtnnXbF8tmwAZ2hgAuuBAoX5dGQt5RQW59RZaAQjPh8Ad4HN8E:1qM20A:7s3dBbPP_Li-In8S2lAB1dA5F6hrMvREMG42jJZabWI", "expire_date": "2023-08-02T07:53:38.639Z"}}, {"model": "sessions.session", "pk": "2kxb11ob0z7ir645yuuokmn3ci98w7pr", "fields": {"session_data": ".eJxVjMsOwiAQRf-FtSE4yMul-34DgZlBqoYmpV0Z_92QdKHbe865bxHTvtW4d17jTOIqQJx-t5zwyW0AeqR2XyQubVvnLIciD9rltBC_bof7d1BTr6MmT6C1QQWqEHtnnXbF8tmwAZ2hgAuuBAoX5dGQt5RQW59RZaAQjPh8Ad4HN8E:1qLfqL:uQqlfFD2O4iFghAo5od0Xr8DkdrLH3CV2OHuiaL0Wz4", "expire_date": "2023-08-01T08:14:01.155Z"}}, {"model": "sessions.session", "pk": "5hmfugbt8shwz9ni58z9msiqx8peard5", "fields": {"session_data": ".eJxVjEEOwiAQRe_C2hCgTKEu3XsGMgODVA0kpV0Z765NutDtf-_9lwi4rSVsnZcwJ3EWWpx-N8L44LqDdMd6azK2ui4zyV2RB-3y2hI_L4f7d1Cwl2-tImlEl_PklcoenNUjO5VHAJ5MTOyBIkfWxlg7aM1kfAJQwIbS4K14fwDpQzfN:1qMMw0:Yt5aAJJ7JX0Nf9yejZ79pymDZyVS7i5AxJz6E3wsado", "expire_date": "2023-08-03T06:14:44.962Z"}}, {"model": "sessions.session", "pk": "5sf4tqt2bknc98utavj1q1320ps9pk0i", "fields": {"session_data": ".eJxVjMsOwiAQRf-FtSE4yMul-34DgZlBqoYmpV0Z_92QdKHbe865bxHTvtW4d17jTOIqQJx-t5zwyW0AeqR2XyQubVvnLIciD9rltBC_bof7d1BTr6MmT6C1QQWqEHtnnXbF8tmwAZ2hgAuuBAoX5dGQt5RQW59RZaAQjPh8Ad4HN8E:1qM0ef:XlmJdqfYM1V8plmB1nlL10CQVdEKVrnA97jQ8NCdvkw", "expire_date": "2023-08-02T06:27:21.930Z"}}, {"model": "sessions.session", "pk": "ew3hykhd4rxailcjcwe3nbgxu60c8gjl", "fields": {"session_data": ".eJxVjEEOwiAQRe_C2hCgTKEu3XsGMgODVA0kpV0Z765NutDtf-_9lwi4rSVsnZcwJ3EWWpx-N8L44LqDdMd6azK2ui4zyV2RB-3y2hI_L4f7d1Cwl2-tImlEl_PklcoenNUjO5VHAJ5MTOyBIkfWxlg7aM1kfAJQwIbS4K14fwDpQzfN:1qLhqn:5CGstBvfY7KrwRr_3m11Cp_j0JyJYDLq-lQ5UZYOyXg", "expire_date": "2023-08-01T10:22:37.564Z"}}, {"model": "sessions.session", "pk": "jagkqeyp2v8e3aaacz06k36v5c5xnend", "fields": {"session_data": ".eJxVjMsOwiAQRf-FtSE4yMul-34DgZlBqoYmpV0Z_92QdKHbe865bxHTvtW4d17jTOIqQJx-t5zwyW0AeqR2XyQubVvnLIciD9rltBC_bof7d1BTr6MmT6C1QQWqEHtnnXbF8tmwAZ2hgAuuBAoX5dGQt5RQW59RZaAQjPh8Ad4HN8E:1qLo4s:bc8W1X6djNno6-N0eY-hmQsWWUu68Nq4TvEE6c8T73E", "expire_date": "2023-08-01T17:01:34.795Z"}}, {"model": "sessions.session", "pk": "kf9i1se0bp0y1n51cart52at8yp7k645", "fields": {"session_data": ".eJxVjEEOwiAQRe_C2hCgTKEu3XsGMgODVA0kpV0Z765NutDtf-_9lwi4rSVsnZcwJ3EWWpx-N8L44LqDdMd6azK2ui4zyV2RB-3y2hI_L4f7d1Cwl2-tImlEl_PklcoenNUjO5VHAJ5MTOyBIkfWxlg7aM1kfAJQwIbS4K14fwDpQzfN:1qKY5Q:xg0VEitZVSCXZwFk7u8wCqtmdLZWKjCfWuqJPthByNw", "expire_date": "2023-07-29T05:44:56.598Z"}}, {"model": "sessions.session", "pk": "l6exu6at4qi7kh6n9za1ynnl2v3bygvv", "fields": {"session_data": ".eJxVjEEOwiAQRe_C2hCgTKEu3XsGMgODVA0kpV0Z765NutDtf-_9lwi4rSVsnZcwJ3EWWpx-N8L44LqDdMd6azK2ui4zyV2RB-3y2hI_L4f7d1Cwl2-tImlEl_PklcoenNUjO5VHAJ5MTOyBIkfWxlg7aM1kfAJQwIbS4K14fwDpQzfN:1qLdUr:Yfo2IaH96I_4MD8xS9-zpnq1bn_jhwJ_xu6eGyLo-Bw", "expire_date": "2023-08-01T05:43:41.197Z"}}, {"model": "sessions.session", "pk": "ly157h72p46xl4frag7y49jsa4zqgan2", "fields": {"session_data": ".eJxVjEEOwiAQRe_C2hCgTKEu3XsGMgODVA0kpV0Z765NutDtf-_9lwi4rSVsnZcwJ3EWWpx-N8L44LqDdMd6azK2ui4zyV2RB-3y2hI_L4f7d1Cwl2-tImlEl_PklcoenNUjO5VHAJ5MTOyBIkfWxlg7aM1kfAJQwIbS4K14fwDpQzfN:1qKbCf:hFx0GgCluQxGeVqsyLawWxM6JyMdkC7KxlLJkD0gTRU", "expire_date": "2023-07-29T09:04:37.853Z"}}, {"model": "sessions.session", "pk": "mzmf6szpjet7ma0u5adojbs0loy7tybf", "fields": {"session_data": ".eJxVjMsOwiAQRf-FtSE4yMul-34DgZlBqoYmpV0Z_92QdKHbe865bxHTvtW4d17jTOIqQJx-t5zwyW0AeqR2XyQubVvnLIciD9rltBC_bof7d1BTr6MmT6C1QQWqEHtnnXbF8tmwAZ2hgAuuBAoX5dGQt5RQW59RZaAQjPh8Ad4HN8E:1qLjMx:7-IXe2RWefaBo7PiLkeegOJBMLP9S0zIW-5Yp3wnw1k", "expire_date": "2023-08-01T11:59:55.612Z"}}, {"model": "sessions.session", "pk": "nyy3ad5h1h8jzr3uicgi4h6yez5vf2wp", "fields": {"session_data": ".eJxVjEEOwiAQRe_C2hCgTKEu3XsGMgODVA0kpV0Z765NutDtf-_9lwi4rSVsnZcwJ3EWWpx-N8L44LqDdMd6azK2ui4zyV2RB-3y2hI_L4f7d1Cwl2-tImlEl_PklcoenNUjO5VHAJ5MTOyBIkfWxlg7aM1kfAJQwIbS4K14fwDpQzfN:1qIOWK:5eTQ7LRwCpirgf1k50BNKn9mkqZILtN78-Mc55T04Zo", "expire_date": "2023-07-23T07:07:48.476Z"}}, {"model": "sessions.session", "pk": "oku1233oc9z53udkcagugth3tphyna5t", "fields": {"session_data": ".eJxVjMsOwiAQRf-FtSE4yMul-34DgZlBqoYmpV0Z_92QdKHbe865bxHTvtW4d17jTOIqQJx-t5zwyW0AeqR2XyQubVvnLIciD9rltBC_bof7d1BTr6MmT6C1QQWqEHtnnXbF8tmwAZ2hgAuuBAoX5dGQt5RQW59RZaAQjPh8Ad4HN8E:1qMS7U:UTfFr4jYKptatxKaFxKAqR6UN5dwtAjxwOvs-Z_nlo4", "expire_date": "2023-08-03T11:46:56.251Z"}}, {"model": "sessions.session", "pk": "p46mzxquh7nokylsicnjnb90n236aorh", "fields": {"session_data": ".eJxVjMsOwiAQRf-FtSE4yMul-34DgZlBqoYmpV0Z_92QdKHbe865bxHTvtW4d17jTOIqQJx-t5zwyW0AeqR2XyQubVvnLIciD9rltBC_bof7d1BTr6MmT6C1QQWqEHtnnXbF8tmwAZ2hgAuuBAoX5dGQt5RQW59RZaAQjPh8Ad4HN8E:1qNshW:qRjz1qlv9GwQ7rndFJc4lv8bhK97ckv02wwDFa5RSbY", "expire_date": "2023-08-07T10:22:02.126Z"}}, {"model": "sessions.session", "pk": "qs5id2hra8f8wepo5jfy324t7tcx8k1e", "fields": {"session_data": ".eJxVjMsOwiAQRf-FtSE4yMul-34DgZlBqoYmpV0Z_92QdKHbe865bxHTvtW4d17jTOIqQJx-t5zwyW0AeqR2XyQubVvnLIciD9rltBC_bof7d1BTr6MmT6C1QQWqEHtnnXbF8tmwAZ2hgAuuBAoX5dGQt5RQW59RZaAQjPh8Ad4HN8E:1qLngd:AKlz7WAFDNQ8PdOwYGaV6L-fr-HvZ1LI8L1JTFdVDHM", "expire_date": "2023-08-01T16:36:31.207Z"}}, {"model": "sessions.session", "pk": "tdnntxqyiad8sqgvrlp5pcni103u23wp", "fields": {"session_data": ".eJxVjMsOwiAQRf-FtSE4yMul-34DgZlBqoYmpV0Z_92QdKHbe865bxHTvtW4d17jTOIqQJx-t5zwyW0AeqR2XyQubVvnLIciD9rltBC_bof7d1BTr6MmT6C1QQWqEHtnnXbF8tmwAZ2hgAuuBAoX5dGQt5RQW59RZaAQjPh8Ad4HN8E:1qM1aO:G9qQix5dahYXfBiDzGeCLEMEowr-HlpEbyo52P65_yE", "expire_date": "2023-08-02T07:27:00.158Z"}}, {"model": "sessions.session", "pk": "tz0qlcj6t1ioegy7aj1oo5h9269isqrs", "fields": {"session_data": ".eJxVjEEOwiAQRe_C2hCgTKEu3XsGMgODVA0kpV0Z765NutDtf-_9lwi4rSVsnZcwJ3EWWpx-N8L44LqDdMd6azK2ui4zyV2RB-3y2hI_L4f7d1Cwl2-tImlEl_PklcoenNUjO5VHAJ5MTOyBIkfWxlg7aM1kfAJQwIbS4K14fwDpQzfN:1qM4bQ:A1gurOW9GFQL2FXDtS31BDwEZouwXgsmcrK9bxiXvWI", "expire_date": "2023-08-02T10:40:16.251Z"}}, {"model": "sessions.session", "pk": "xtjnfuaprasha9kpmn0tn8pbj5coiukn", "fields": {"session_data": ".eJxVjMsOwiAQRf-FtSE4yMul-34DgZlBqoYmpV0Z_92QdKHbe865bxHTvtW4d17jTOIqQJx-t5zwyW0AeqR2XyQubVvnLIciD9rltBC_bof7d1BTr6MmT6C1QQWqEHtnnXbF8tmwAZ2hgAuuBAoX5dGQt5RQW59RZaAQjPh8Ad4HN8E:1qLdSf:YzTU8oou7DLE7aT-tmjibBJRRAYPc6qamXVl6Li8jV8", "expire_date": "2023-08-01T05:41:25.382Z"}}, {"model": "sessions.session", "pk": "y4nriywunme4t76xfmym4mklcn2f5sb7", "fields": {"session_data": ".eJxVjMsOwiAQRf-FtSE4yMul-34DgZlBqoYmpV0Z_92QdKHbe865bxHTvtW4d17jTOIqQJx-t5zwyW0AeqR2XyQubVvnLIciD9rltBC_bof7d1BTr6MmT6C1QQWqEHtnnXbF8tmwAZ2hgAuuBAoX5dGQt5RQW59RZaAQjPh8Ad4HN8E:1qLQsT:E8FyBTFkxsz7KQ41HDsYn12NaV5lJE7jg9gwgc0iQfE", "expire_date": "2023-07-31T16:15:13.998Z"}}, {"model": "sessions.session", "pk": "y9ap62c9kzolb5ajhe1vkolg7fdezaef", "fields": {"session_data": ".eJxVjMsOwiAQRf-FtSE4yMul-34DgZlBqoYmpV0Z_92QdKHbe865bxHTvtW4d17jTOIqQJx-t5zwyW0AeqR2XyQubVvnLIciD9rltBC_bof7d1BTr6MmT6C1QQWqEHtnnXbF8tmwAZ2hgAuuBAoX5dGQt5RQW59RZaAQjPh8Ad4HN8E:1qLnhI:buEtuLqu-6q39o7VPYrNU2sOJtqdnoyVHfrD6N1s8lU", "expire_date": "2023-08-01T16:37:12.830Z"}}, {"model": "sessions.session", "pk": "ywn5wu5b1394jqf8jreukvecemao6vjx", "fields": {"session_data": ".eJxVjMsOwiAQRf-FtSE4yMul-34DgZlBqoYmpV0Z_92QdKHbe865bxHTvtW4d17jTOIqQJx-t5zwyW0AeqR2XyQubVvnLIciD9rltBC_bof7d1BTr6MmT6C1QQWqEHtnnXbF8tmwAZ2hgAuuBAoX5dGQt5RQW59RZaAQjPh8Ad4HN8E:1qNpdR:Fut20kehXVr76OjQxpQ60zjcgoA4g1HKgNgnkPsxD0k", "expire_date": "2023-08-07T07:05:37.504Z"}}, {"model": "sessions.session", "pk": "z3qvrdkzgg8ltksj23zhzmiz7q3opzem", "fields": {"session_data": ".eJxVjMsOwiAQRf-FtSE4yMul-34DgZlBqoYmpV0Z_92QdKHbe865bxHTvtW4d17jTOIqQJx-t5zwyW0AeqR2XyQubVvnLIciD9rltBC_bof7d1BTr6MmT6C1QQWqEHtnnXbF8tmwAZ2hgAuuBAoX5dGQt5RQW59RZaAQjPh8Ad4HN8E:1qLdiA:yNZtpugiZcuT5tJRjT94BMyeNnkU1YSzLSQa0bpHnbQ", "expire_date": "2023-08-01T05:57:26.948Z"}}, {"model": "cars.car", "pk": 1, "fields": {"make": "Fiat", "model": "500", "version": "1.2 Lounge", "price": "7.300,00", "year": "2012", "gear": "Manual", "fuel": "Petrol", "mileage": "126,200", "power": "52 kW", "optionals": "Bluethoot, Blue&Me, Panoramic Roof", "description": "Last service two weeks ago", "created_at": "2023-07-24", "miniature": "istockphoto_LhltphG.jpeg", "slug": "fiat-12l9vt", "showcase": true}}, {"model": "cars.car", "pk": 2, "fields": {"make": "Mercedes", "model": "Classe A 180", "version": "CDI Sport", "price": "14.400,00", "year": "2016", "gear": "Automatic", "fuel": "Diesel", "mileage": "171,000", "power": "80 kW", "optionals": "Parking sensors posteriors and anteriors", "description": "a wonderful car", "created_at": "2023-07-20", "miniature": "mercedes-3489627_1280.jpg", "slug": "mercedes-A80ht78", "showcase": true}}, {"model": "cars.car", "pk": 3, "fields": {"make": "BMW", "model": "320", "version": "320d Touring", "price": "9.900,00", "year": "2016", "gear": "Automatic", "fuel": "Diesel", "mileage": "256,000", "power": "140 kW", "optionals": "Bluethoot, CD, Airbag, Isofix", "description": "Vehicle only for sellers", "created_at": "2023-07-20", "miniature": "bmw320.jpeg", "slug": "bm2-320swt678h", "showcase": true}}, {"model": "cars.car", "pk": 4, "fields": {"make": "Audi", "model": "A1", "version": "SPB 1.6 TDI 116 CV", "price": "13.470,00", "year": "2016", "gear": "Manual", "fuel": "Diesel", "mileage": "115,119", "power": "85 kW", "optionals": "Bluethoot, Panoramic Roof", "description": "This vehicle is from Germany", "created_at": "2023-07-20", "miniature": "a1.jpeg", "slug": "audi-1ht6zw", "showcase": true}}, {"model": "cars.car", "pk": 5, "fields": {"make": "Audi", "model": "A3", "version": "SPB 1.6 TDI clean diesel", "price": "11.950,00", "year": "2016", "gear": "Manual", "fuel": "Diesel", "mileage": "219,000", "power": "81 kW", "optionals": "Commands on Steele wheels", "description": "Beautiful car", "created_at": "2023-07-20", "miniature": "a3.jpeg", "slug": "audi45-23252sds", "showcase": true}}, {"model": "cars.car", "pk": 6, "fields": {"make": "Porsche", "model": "Macan", "version": "S diesel PDK", "price": "34.000,00", "year": "2016", "gear": "Automatic", "fuel": "Diesel", "mileage": "164,250", "power": "184,000", "optionals": "Full optional", "description": "This car is amazing", "created_at": "2023-07-20", "miniature": "macan.jpeg", "slug": "porsche-3e4519sa", "showcase": true}}, {"model": "cars.car", "pk": 7, "fields": {"make": "Ford", "model": "Focus", "version": "SW 1.5 ecoblue Business", "price": "8.300,00", "year": "2018", "gear": "Manual", "fuel": "Diesel", "mileage": "86,700", "power": "88 kW", "optionals": "Bluethoot", "description": "Last service this week", "created_at": "2023-07-20", "miniature": "focus.jpeg", "slug": "ford-f78sahsbo1", "showcase": false}}, {"model": "cars.car", "pk": 8, "fields": {"make": "Mercedes", "model": "B 180", "version": "Sport", "price": "11.500,00", "year": "2014", "gear": "Automatic", "fuel": "Diesel", "mileage": "189,000", "power": "84", "optionals": "Panoramic Roof, Bluethoot, Parking Sensors, Apple Car Play, Mercedes Me", "description": "This car will arrive next week.", "created_at": "2023-07-22", "miniature": "", "slug": "mercedes-b671gf8o", "showcase": false}}, {"model": "cars.companyinfo", "pk": 1, "fields": {"address": "Company Street, City, Nation", "phoneNumber": "(+39) 333 88811122", "email": "carhub@info.com", "idCode": "Company ID"}}, {"model": "newsletter.subscriber", "pk": 5, "fields": {"email": "alessiomirra97@gmail.com", "date_subscibed": "2023-07-22T14:54:48.671Z"}}]